{
    "analyses": {
        "7c71d12e-aff9-419f-a533-14c037496ead": ">",
        "eaa81a36-9860-4757-91d3-c84da6479863": "1.5",
        "418979e0-5b3b-46c2-b6b3-264e985dd138": "1.7",
        "f3907cf0-6d30-4e15-bac6-a253afc42759": {
            "title": "title",
            "description": "some description"
        },
        "c9f218c0-a7f7-48b3-9c39-99970ec3fa16": "5",
        "6261fb21-c609-44c7-bdfc-e7eb021d8c25": {
            "title": "1",
            "description": "Пывоывлалывлыав рвыфвnстывстоывсэn"
        },
        "fb3aee0a-45af-4ce1-94d6-384dd6f2cb17": {
            "title": "0"
        },
        "046a0991-03da-4e33-aebd-de4bf1dcdbb1": "0",
        "316b91a6-ca0d-4c37-99ff-6d2d95bed68d": "3",
        "865b9e95-7e7e-4be7-855e-ce11c651e23e": "2",
        "f0219c49-d5e9-4ce1-b6c4-8149365adb79": "5",
        "40c6ca44-496c-40fe-be9b-c36715c762d9": "<=",
        "e06399e8-83f3-4323-a7ee-2922cd9c84f8": "Vitamin b2",
        "3e4a4ff0-d10f-4044-a3ca-b595457a4c26": "Vitamin b2",
        "2943394b-a968-4e2c-8866-4c65350d0c40": "some new Analyse 1",
        "28b2fec6-c27c-4292-9ca1-f7d60355cc21": {
            "title": "result"
        }
    },
    "diagramData": {
        "id": "8f558fef-73d8-446a-9487-a2d0a6bc1885",
        "offsetX": -142.00692711420922,
        "offsetY": 280.51822159113016,
        "zoom": 58.66666941444097,
        "gridSize": 0,
        "layers": [
            {
                "id": "38a62db2-de1a-4619-8894-76a0a730cecd",
                "type": "diagram-links",
                "isSvg": true,
                "transformed": true,
                "models": {
                    "9b9fcbdf-a574-4ef8-bd86-2533a671c586": {
                        "id": "9b9fcbdf-a574-4ef8-bd86-2533a671c586",
                        "type": "default",
                        "selected": false,
                        "source": "c9f218c0-a7f7-48b3-9c39-99970ec3fa16",
                        "sourcePort": "c4d3ea3f-8413-4773-bd30-c897e8583717",
                        "target": "ee71a111-f6ce-41c9-aa69-5c8342159a14",
                        "targetPort": "a370515d-b125-4d94-83a3-e4cddfa7d627",
                        "points": [
                            {
                                "id": "4cda4f79-09e3-4b4c-900f-0ddf12b589d3",
                                "type": "point",
                                "x": 101.74998696398306,
                                "y": 22.296882707037923
                            },
                            {
                                "id": "6307a2fa-15aa-4a5f-b2ec-18321c356e64",
                                "type": "point",
                                "x": 226.31252205113782,
                                "y": -33.45311190747085
                            }
                        ],
                        "labels": [],
                        "width": 3,
                        "color": "gray",
                        "curvyness": 50,
                        "selectedColor": "rgb(0,192,255)"
                    },
                    "95e3886b-0139-40ac-8712-07764fcfa47c": {
                        "id": "95e3886b-0139-40ac-8712-07764fcfa47c",
                        "type": "default",
                        "selected": false,
                        "source": "ee71a111-f6ce-41c9-aa69-5c8342159a14",
                        "sourcePort": "68d22160-3ca3-4956-a3c2-bc3bb89ced1a",
                        "target": "2c8f5891-d464-4915-a61c-ecfa75b43a00",
                        "targetPort": "8830128c-1c5f-4f8a-93a9-096463de6603",
                        "points": [
                            {
                                "id": "282db145-7b95-44ba-a90b-a439aab150c7",
                                "type": "point",
                                "x": 308.3125050324545,
                                "y": -45.953128661539814
                            },
                            {
                                "id": "b3aeb5ba-0239-4f61-9d14-50d06a4a9ddb",
                                "type": "point",
                                "x": 454.40621351078835,
                                "y": -41.51563025654185
                            }
                        ],
                        "labels": [],
                        "width": 3,
                        "color": "gray",
                        "curvyness": 50,
                        "selectedColor": "rgb(0,192,255)"
                    },
                    "a186e6ff-3330-47a2-9828-4036f61a0806": {
                        "id": "a186e6ff-3330-47a2-9828-4036f61a0806",
                        "type": "default",
                        "selected": false,
                        "source": "0966429e-c96e-44f3-a3b3-c5524dd1cb92",
                        "sourcePort": "46c296b2-615c-4a84-abd6-12fcb386ca02",
                        "target": null,
                        "targetPort": null,
                        "points": [
                            {
                                "id": "74e8fbdf-5b0b-4850-b918-0bddf6787879",
                                "type": "point",
                                "x": 1275.5155999902922,
                                "y": -91.28124945775986
                            },
                            {
                                "id": "863e7490-cb4d-48dd-8988-e75995aeaec5",
                                "type": "point",
                                "x": 1491.4890104513481,
                                "y": -287.24695516744123
                            }
                        ],
                        "labels": [],
                        "width": 3,
                        "color": "gray",
                        "curvyness": 50,
                        "selectedColor": "rgb(0,192,255)"
                    },
                    "89e792a1-5e15-404f-bda8-87181aba7f04": {
                        "id": "89e792a1-5e15-404f-bda8-87181aba7f04",
                        "type": "default",
                        "selected": false,
                        "source": "0966429e-c96e-44f3-a3b3-c5524dd1cb92",
                        "sourcePort": "55a39c0d-c7cd-4ce8-84a4-166e764de0c1",
                        "target": "28b2fec6-c27c-4292-9ca1-f7d60355cc21",
                        "targetPort": "91d1b57f-c63b-47e2-adf1-32b38e59ff01",
                        "points": [
                            {
                                "id": "59d4a9d8-6029-4f02-a7c6-ed3aa3f623f9",
                                "type": "point",
                                "x": 1275.5155999902922,
                                "y": -35.281253467797775
                            },
                            {
                                "id": "ce775d73-c613-4ecd-b6bf-b48073883e77",
                                "type": "point",
                                "x": 1479.9843695439913,
                                "y": 108.32809885359171
                            }
                        ],
                        "labels": [],
                        "width": 3,
                        "color": "gray",
                        "curvyness": 50,
                        "selectedColor": "rgb(0,192,255)"
                    },
                    "064b63c4-379e-4ea6-aa24-815efe10f7ce": {
                        "id": "064b63c4-379e-4ea6-aa24-815efe10f7ce",
                        "type": "default",
                        "selected": false,
                        "source": "e06399e8-83f3-4323-a7ee-2922cd9c84f8",
                        "sourcePort": "0710559c-468c-48ea-a8d0-cde60070e356",
                        "target": "ee71a111-f6ce-41c9-aa69-5c8342159a14",
                        "targetPort": "9955dfe9-171e-4432-9e6c-7659a0c94d1b",
                        "points": [
                            {
                                "id": "3ec99663-56c8-4393-8319-43b1d6ba9a86",
                                "type": "point",
                                "x": 95.09379137508274,
                                "y": -72.57814510082595
                            },
                            {
                                "id": "824c31c3-d595-4a67-bc95-48f775762cb7",
                                "type": "point",
                                "x": 226.31252205113782,
                                "y": -58.45314541560878
                            }
                        ],
                        "labels": [],
                        "width": 3,
                        "color": "gray",
                        "curvyness": 50,
                        "selectedColor": "rgb(0,192,255)"
                    },
                    "9f787bbe-32ca-4baf-a66a-d78380042cde": {
                        "id": "9f787bbe-32ca-4baf-a66a-d78380042cde",
                        "type": "default",
                        "selected": false,
                        "source": "3e4a4ff0-d10f-4044-a3ca-b595457a4c26",
                        "sourcePort": "6bb55f1d-d0dd-407b-b12e-6662d9624558",
                        "target": "2c8f5891-d464-4915-a61c-ecfa75b43a00",
                        "targetPort": "ee9d0cea-bd43-4aec-91ed-2b29b0388547",
                        "points": [
                            {
                                "id": "701d01a6-f46f-460f-80da-3722a2bb5d04",
                                "type": "point",
                                "x": 820.6718574222105,
                                "y": -169.7343704364555
                            },
                            {
                                "id": "0d9ebfe9-d568-4391-a35e-a4e372675019",
                                "type": "point",
                                "x": 646.2031488857156,
                                "y": -69.51562825152288
                            }
                        ],
                        "labels": [],
                        "width": 3,
                        "color": "gray",
                        "curvyness": 50,
                        "selectedColor": "rgb(0,192,255)"
                    },
                    "453222c5-5673-4d54-8c8f-4cf60f8e6eac": {
                        "id": "453222c5-5673-4d54-8c8f-4cf60f8e6eac",
                        "type": "default",
                        "selected": false,
                        "source": "3e4a4ff0-d10f-4044-a3ca-b595457a4c26",
                        "sourcePort": "3df923fb-aac9-4e10-bb8e-068a77153df9",
                        "target": "0966429e-c96e-44f3-a3b3-c5524dd1cb92",
                        "targetPort": "79a62ab1-4165-4ad9-bead-eb4309758aa9",
                        "points": [
                            {
                                "id": "69c43710-5a45-47b8-a795-6a37056b8f89",
                                "type": "point",
                                "x": 877.4844359102908,
                                "y": -169.7343704364555
                            },
                            {
                                "id": "42137da0-3614-4758-a975-64d1577d7acf",
                                "type": "point",
                                "x": 1083.718664615365,
                                "y": -63.28125146277882
                            }
                        ],
                        "labels": [],
                        "width": 3,
                        "color": "gray",
                        "curvyness": 50,
                        "selectedColor": "rgb(0,192,255)"
                    }
                }
            },
            {
                "id": "3f1acbf4-b79d-40b0-8f6e-c24e740a1bda",
                "type": "diagram-nodes",
                "isSvg": false,
                "transformed": true,
                "models": {
                    "c9f218c0-a7f7-48b3-9c39-99970ec3fa16": {
                        "id": "c9f218c0-a7f7-48b3-9c39-99970ec3fa16",
                        "locked": false,
                        "type": "data",
                        "selected": false,
                        "x": 31.75355716861357,
                        "y": -5.213266031720735,
                        "ports": [
                            {
                                "id": "c4d3ea3f-8413-4773-bd30-c897e8583717",
                                "type": "default",
                                "x": 91.74993194585058,
                                "y": 12.296879707502077,
                                "name": "data-out-blue",
                                "alignment": "right",
                                "parentNode": "c9f218c0-a7f7-48b3-9c39-99970ec3fa16",
                                "links": [
                                    "9b9fcbdf-a574-4ef8-bd86-2533a671c586"
                                ],
                                "in": false,
                                "label": "data-out-blue"
                            }
                        ]
                    },
                    "ee71a111-f6ce-41c9-aa69-5c8342159a14": {
                        "id": "ee71a111-f6ce-41c9-aa69-5c8342159a14",
                        "type": "operator",
                        "selected": false,
                        "x": 212.3222704933235,
                        "y": -73.45970886310715,
                        "ports": [
                            {
                                "id": "68d22160-3ca3-4956-a3c2-bc3bb89ced1a",
                                "type": "default",
                                "x": 298.312450014322,
                                "y": -55.95313166107566,
                                "name": "operator-out-blue",
                                "alignment": "right",
                                "parentNode": "ee71a111-f6ce-41c9-aa69-5c8342159a14",
                                "links": [
                                    "95e3886b-0139-40ac-8712-07764fcfa47c"
                                ],
                                "in": false,
                                "label": "operator-out-blue"
                            },
                            {
                                "id": "9955dfe9-171e-4432-9e6c-7659a0c94d1b",
                                "type": "default",
                                "x": 216.31251905160198,
                                "y": -68.45314841514463,
                                "name": "operator-in-blue",
                                "alignment": "left",
                                "parentNode": "ee71a111-f6ce-41c9-aa69-5c8342159a14",
                                "links": [
                                    "064b63c4-379e-4ea6-aa24-815efe10f7ce"
                                ],
                                "in": true,
                                "label": "operator-in-blue"
                            },
                            {
                                "id": "a370515d-b125-4d94-83a3-e4cddfa7d627",
                                "type": "default",
                                "x": 216.31251905160198,
                                "y": -43.45311490700669,
                                "name": "operator-in-red",
                                "alignment": "left",
                                "parentNode": "ee71a111-f6ce-41c9-aa69-5c8342159a14",
                                "links": [
                                    "9b9fcbdf-a574-4ef8-bd86-2533a671c586"
                                ],
                                "in": true,
                                "label": "operator-in-red"
                            }
                        ]
                    },
                    "2c8f5891-d464-4915-a61c-ecfa75b43a00": {
                        "id": "2c8f5891-d464-4915-a61c-ecfa75b43a00",
                        "type": "branching",
                        "selected": false,
                        "x": 397.96665983384014,
                        "y": -139.02307492775782,
                        "ports": [
                            {
                                "id": "ee9d0cea-bd43-4aec-91ed-2b29b0388547",
                                "type": "default",
                                "x": 604.453127259399,
                                "y": -81.51564225468523,
                                "name": "branching-out-true",
                                "alignment": "right",
                                "parentNode": "2c8f5891-d464-4915-a61c-ecfa75b43a00",
                                "links": [
                                    "9f787bbe-32ca-4baf-a66a-d78380042cde"
                                ],
                                "in": false,
                                "label": "branching-out-true"
                            },
                            {
                                "id": "7c2d583a-3cf6-42aa-9378-fc6bf2659ab4",
                                "type": "default",
                                "x": 604.453127259399,
                                "y": -25.515646264723145,
                                "name": "branching-out-false",
                                "alignment": "right",
                                "parentNode": "2c8f5891-d464-4915-a61c-ecfa75b43a00",
                                "links": [],
                                "in": false,
                                "label": "branching-out-false"
                            },
                            {
                                "id": "8830128c-1c5f-4f8a-93a9-096463de6603",
                                "type": "default",
                                "x": 407.9530865250284,
                                "y": -53.51564425970419,
                                "name": "branching-in-condition",
                                "alignment": "left",
                                "parentNode": "2c8f5891-d464-4915-a61c-ecfa75b43a00",
                                "links": [
                                    "95e3886b-0139-40ac-8712-07764fcfa47c"
                                ],
                                "in": true,
                                "label": "branching-in-condition"
                            }
                        ]
                    },
                    "ed7a36f0-608f-4729-bb89-54762883f131": {
                        "id": "ed7a36f0-608f-4729-bb89-54762883f131",
                        "type": "result",
                        "selected": false,
                        "x": 1449.9999367699693,
                        "y": -428.4090661599628,
                        "ports": [
                            {
                                "id": "5397a5d7-370f-44e9-8da3-d65668316517",
                                "type": "default",
                                "x": 1469.984314525859,
                                "y": -286.9062593687455,
                                "name": "result-in-port",
                                "alignment": "left",
                                "parentNode": "ed7a36f0-608f-4729-bb89-54762883f131",
                                "links": [],
                                "in": true,
                                "label": "result-in-port"
                            }
                        ]
                    },
                    "0966429e-c96e-44f3-a3b3-c5524dd1cb92": {
                        "id": "0966429e-c96e-44f3-a3b3-c5524dd1cb92",
                        "type": "branching",
                        "selected": false,
                        "x": 1027.2726838419992,
                        "y": -160.79544233056228,
                        "ports": [
                            {
                                "id": "46c296b2-615c-4a84-abd6-12fcb386ca02",
                                "type": "default",
                                "x": 1233.7655783639757,
                                "y": -103.28126346092219,
                                "name": "branching-out-true",
                                "alignment": "right",
                                "parentNode": "0966429e-c96e-44f3-a3b3-c5524dd1cb92",
                                "links": [
                                    "a186e6ff-3330-47a2-9828-4036f61a0806"
                                ],
                                "in": false,
                                "label": "branching-out-true"
                            },
                            {
                                "id": "55a39c0d-c7cd-4ce8-84a4-166e764de0c1",
                                "type": "default",
                                "x": 1233.7655783639757,
                                "y": -47.28126747096012,
                                "name": "branching-out-false",
                                "alignment": "right",
                                "parentNode": "0966429e-c96e-44f3-a3b3-c5524dd1cb92",
                                "links": [
                                    "89e792a1-5e15-404f-bda8-87181aba7f04"
                                ],
                                "in": false,
                                "label": "branching-out-false"
                            },
                            {
                                "id": "79a62ab1-4165-4ad9-bead-eb4309758aa9",
                                "type": "default",
                                "x": 1037.2655376296052,
                                "y": -75.28126546594116,
                                "name": "branching-in-condition",
                                "alignment": "left",
                                "parentNode": "0966429e-c96e-44f3-a3b3-c5524dd1cb92",
                                "links": [
                                    "453222c5-5673-4d54-8c8f-4cf60f8e6eac"
                                ],
                                "in": true,
                                "label": "branching-in-condition"
                            }
                        ]
                    },
                    "28b2fec6-c27c-4292-9ca1-f7d60355cc21": {
                        "id": "28b2fec6-c27c-4292-9ca1-f7d60355cc21",
                        "locked": false,
                        "type": "result",
                        "selected": true,
                        "x": 1449.9999367699693,
                        "y": -43.18181147560282,
                        "ports": [
                            {
                                "id": "91d1b57f-c63b-47e2-adf1-32b38e59ff01",
                                "type": "default",
                                "x": 1469.984314525859,
                                "y": 98.32809585405587,
                                "name": "result-in-port",
                                "alignment": "left",
                                "parentNode": "28b2fec6-c27c-4292-9ca1-f7d60355cc21",
                                "links": [
                                    "89e792a1-5e15-404f-bda8-87181aba7f04"
                                ],
                                "in": true,
                                "label": "result-in-port"
                            }
                        ]
                    },
                    "e06399e8-83f3-4323-a7ee-2922cd9c84f8": {
                        "id": "e06399e8-83f3-4323-a7ee-2922cd9c84f8",
                        "type": "parameter",
                        "selected": false,
                        "x": 23.295458138069918,
                        "y": -121.59089871224245,
                        "ports": [
                            {
                                "id": "0710559c-468c-48ea-a8d0-cde60070e356",
                                "type": "default",
                                "x": 80.0938128850773,
                                "y": -87.57814960012972,
                                "name": "Parameter-out-port",
                                "alignment": "right",
                                "parentNode": "e06399e8-83f3-4323-a7ee-2922cd9c84f8",
                                "links": [
                                    "064b63c4-379e-4ea6-aa24-815efe10f7ce"
                                ],
                                "in": false,
                                "label": "Parameter-out-port"
                            },
                            {
                                "id": "e86a9d25-f29f-4d09-98d0-1243c36b1f3d",
                                "type": "default",
                                "x": 23.281234396996993,
                                "y": -87.57814960012972,
                                "name": "Parameter-in-port",
                                "alignment": "left",
                                "parentNode": "e06399e8-83f3-4323-a7ee-2922cd9c84f8",
                                "links": [],
                                "in": true,
                                "label": "Parameter-in-port"
                            }
                        ]
                    },
                    "3e4a4ff0-d10f-4044-a3ca-b595457a4c26": {
                        "id": "3e4a4ff0-d10f-4044-a3ca-b595457a4c26",
                        "type": "parameter",
                        "selected": false,
                        "x": 805.6817851297567,
                        "y": -218.74998507068722,
                        "ports": [
                            {
                                "id": "3df923fb-aac9-4e10-bb8e-068a77153df9",
                                "type": "default",
                                "x": 862.4844054016887,
                                "y": -184.73437493575926,
                                "name": "Parameter-out-port",
                                "alignment": "right",
                                "parentNode": "3e4a4ff0-d10f-4044-a3ca-b595457a4c26",
                                "links": [
                                    "453222c5-5673-4d54-8c8f-4cf60f8e6eac"
                                ],
                                "in": false,
                                "label": "Parameter-out-port"
                            },
                            {
                                "id": "6bb55f1d-d0dd-407b-b12e-6662d9624558",
                                "type": "default",
                                "x": 805.671878932205,
                                "y": -184.73437493575926,
                                "name": "Parameter-in-port",
                                "alignment": "left",
                                "parentNode": "3e4a4ff0-d10f-4044-a3ca-b595457a4c26",
                                "links": [
                                    "9f787bbe-32ca-4baf-a66a-d78380042cde"
                                ],
                                "in": true,
                                "label": "Parameter-in-port"
                            }
                        ]
                    }
                }
            }
        ]
    }
}
